LICENSE
MANIFEST.in
setup.py
django_taggit_live.egg-info/PKG-INFO
django_taggit_live.egg-info/SOURCES.txt
django_taggit_live.egg-info/dependency_links.txt
django_taggit_live.egg-info/not-zip-safe
django_taggit_live.egg-info/requires.txt
django_taggit_live.egg-info/top_level.txt
taggit_live/__init__.py
taggit_live/forms.py
taggit_live/urls.py
taggit_live/views.py
taggit_live/static/taggit_live/css/taggit_live.css
taggit_live/static/taggit_live/js/taggit_live.js