Metadata-Version: 1.1
Name: django-taggit-live
Version: 0.0.4
Summary: It's an autocomplete widget for django-taggit TagField
Home-page: https://github.com/20tab/django-taggit-live
Author: 20tab srl: Raffaele Colace
Author-email: info@20tab.com
License: Mit License
Platform: OS Independent
Classifier: Environment :: Web Environment
Classifier: Framework :: Django
Classifier: Intended Audience :: Developers
Classifier: Operating System :: OS Independent
Classifier: Programming Language :: Python
Classifier: Topic :: Internet :: WWW/HTTP :: Dynamic Content
Classifier: Topic :: Software Development
Classifier: Topic :: Software Development :: Libraries :: Application Frameworks
